pyenforce/__init__.py
pyenforce/__main__.py
pyenforce/cli.py
pyenforce/runner.py
pyenforce/tools.py
pyenforce/utils.py
pyenforce/configs/bandit.toml
pyenforce/configs/mypy.toml
pyenforce/configs/pylint.toml
pyenforce/configs/ruff.toml
pyenforce/configs/vulture.toml
pyenforce-0.1.0.dist-info/licenses/LICENSE
pyenforce-0.1.0.dist-info/METADATA
pyenforce-0.1.0.dist-info/WHEEL
pyenforce-0.1.0.dist-info/entry_points.txt
pyenforce-0.1.0.dist-info/top_level.txt
pyenforce-0.1.0.dist-info/RECORD
