Metadata-Version: 2.4
Name: pyenforce
Version: 0.1.0
Summary: A comprehensive quality assurance CLI for enforcing strict Python code standards.
Author-email: HH-MWB <h.hong@mail.com>
License: MIT
Project-URL: Homepage, https://HH-MWB.github.io/pyenforce
Project-URL: Repository, https://github.com/HH-MWB/pyenforce
Project-URL: Issues, https://github.com/HH-MWB/pyenforce/issues
Keywords: code-quality,linting,static-analysis,type-checking,security,ruff,mypy,pylint,bandit,semgrep,vulture,pre-commit,ci
Classifier: Development Status :: 3 - Alpha
Classifier: Intended Audience :: Developers
Classifier: License :: OSI Approved :: MIT License
Classifier: Operating System :: OS Independent
Classifier: Programming Language :: Python
Classifier: Programming Language :: Python :: 3
Classifier: Programming Language :: Python :: 3.11
Classifier: Programming Language :: Python :: 3.12
Classifier: Programming Language :: Python :: 3.13
Classifier: Topic :: Software Development
Classifier: Topic :: Software Development :: Quality Assurance
Classifier: Topic :: Software Development :: Testing
Classifier: Topic :: Utilities
Requires-Python: >=3.11
License-File: LICENSE
Provides-Extra: all
Requires-Dist: bandit==1.9.2; extra == "all"
Requires-Dist: mypy==1.19.1; extra == "all"
Requires-Dist: pylint==4.0.4; extra == "all"
Requires-Dist: ruff==0.14.10; extra == "all"
Requires-Dist: semgrep==1.146.0; extra == "all"
Requires-Dist: vulture==2.14; extra == "all"
Provides-Extra: bandit
Requires-Dist: bandit==1.9.2; extra == "bandit"
Provides-Extra: mypy
Requires-Dist: mypy==1.19.1; extra == "mypy"
Provides-Extra: pylint
Requires-Dist: pylint==4.0.4; extra == "pylint"
Provides-Extra: ruff
Requires-Dist: ruff==0.14.10; extra == "ruff"
Provides-Extra: semgrep
Requires-Dist: semgrep==1.146.0; extra == "semgrep"
Provides-Extra: vulture
Requires-Dist: vulture==2.14; extra == "vulture"
Dynamic: license-file
